{
    "landmarks": [
        [
            [
                0.4541577347202796,
                0.7053216982998519,
                0.014056629206048723
            ],
            [
                0.4826997513182068,
                0.6567689907356231,
                -0.008682127902162703
            ],
            [
                0.5226845810223527,
                0.6165224807006066,
                -0.005079219721162823
            ],
            [
                0.5526193886715857,
                0.598561500059377,
                -0.0006450985176246603
            ],
            [
                0.5756593454089315,
                0.5931036677347504,
                -0.014155965288074704
            ],
            [
                0.59321053413887,
                0.6167496968955588,
                4.03390212624366e-05
            ],
            [
                0.6365914834207579,
                0.5693635799806125,
                -0.021440944878683206
            ],
            [
                0.672460835555476,
                0.5127405008511181,
                -0.030853037181019602
            ],
            [
                0.7127633340986669,
                0.4655526993465892,
                -0.04501138052640745
            ],
            [
                0.5918895714859186,
                0.6232855454760271,
                -0.004908472210984852
            ],
            [
                0.6392550692994127,
                0.5693691837482603,
                -0.027577890081584115
            ],
            [
                0.6840816831528841,
                0.5231583284702425,
                -0.05706667748032371
            ],
            [
                0.7092883750053219,
                0.4572352098253344,
                -0.06035359508709807
            ],
            [
                0.6006548264298166,
                0.6200777285893371,
                -0.011292828154256007
            ],
            [
                0.6384805745247889,
                0.5616549531039227,
                -0.030699935026481807
            ],
            [
                0.676912009166369,
                0.5197858044241973,
                -0.053844395531062114
            ],
            [
                0.6993488833171488,
                0.4795912456202746,
                -0.04862510441186557
            ],
            [
                0.58868999599544,
                0.6196210964723845,
                -0.03037449982593085
            ],
            [
                0.6344146896800104,
                0.5809336899711434,
                -0.035098487803538206
            ],
            [
                0.671400065391979,
                0.541938029903627,
                -0.047213599340871513
            ],
            [
                0.6937347677063321,
                0.5155605530499431,
                -0.05323476831184088
            ]
        ],
        [
            [
                0,
                0,
                0
            ],
            [
                0,
                0,
                0
            ],
            [
                0,
                0,
                0
            ],
            [
                0,
                0,
                0
            ],
            [
                0,
                0,
                0
            ],
            [
                0,
                0,
                0
            ],
            [
                0,
                0,
                0
            ],
            [
                0,
                0,
                0
            ],
            [
                0,
                0,
                0
            ],
            [
                0,
                0,
                0
            ],
            [
                0,
                0,
                0
            ],
            [
                0,
                0,
                0
            ],
            [
                0,
                0,
                0
            ],
            [
                0,
                0,
                0
            ],
            [
                0,
                0,
                0
            ],
            [
                0,
                0,
                0
            ],
            [
                0,
                0,
                0
            ],
            [
                0,
                0,
                0
            ],
            [
                0,
                0,
                0
            ],
            [
                0,
                0,
                0
            ],
            [
                0,
                0,
                0
            ]
        ]
    ],
    "label": "U",
    "is_dual_hand": false,
    "augmented": true,
    "augmentation_methods": [
        "_apply_translation",
        "_apply_noise"
    ]
}