{
    "landmarks": [
        [
            [
                0.4100869658716433,
                0.9042748585235216,
                0.01897879990425072
            ],
            [
                0.31313376229439693,
                0.7782863972758426,
                -0.137692270644169
            ],
            [
                0.2871856716568398,
                0.6087435770476358,
                -0.1825107381083219
            ],
            [
                0.24468768820817993,
                0.4662240789491594,
                -0.1932797181899384
            ],
            [
                0.1865982809271034,
                0.36424036064379406,
                -0.1775267840671438
            ],
            [
                0.5935245941678524,
                0.58645815451664,
                -0.17198441645580576
            ],
            [
                0.6122722538249804,
                0.3716409533398379,
                -0.16073365544769408
            ],
            [
                0.5528028606710573,
                0.2898646540312549,
                -0.14310176946046693
            ],
            [
                0.5176436131379815,
                0.21499253328080686,
                -0.12613282160479847
            ],
            [
                0.6482529524119045,
                0.6075396864265951,
                -0.06403216135200865
            ],
            [
                0.5194253412373528,
                0.46754444116795313,
                -0.08107173042240459
            ],
            [
                0.4190322671490559,
                0.5131841915980891,
                -0.05217865203411609
            ],
            [
                0.4067031915193575,
                0.5691615975147812,
                -0.024899546256923314
            ],
            [
                0.6443144795860708,
                0.6480080852096161,
                0.016156056746621544
            ],
            [
                0.519569136931324,
                0.5255912626420338,
                0.0010189089056183917
            ],
            [
                0.45999720110305653,
                0.567173693787143,
                0.007110441199500925
            ],
            [
                0.4489093778162397,
                0.6093149599727418,
                0.0018441287856026806
            ],
            [
                0.6418084915915157,
                0.644875088712622,
                0.11697620716721514
            ],
            [
                0.564904442106701,
                0.5600404868985254,
                0.09250519271685644
            ],
            [
                0.5044369575709627,
                0.5865760340767397,
                0.07057955927105793
            ],
            [
                0.49529123793530516,
                0.6471705568868944,
                0.07809579680707747
            ]
        ],
        [
            [
                0,
                0,
                0
            ],
            [
                0,
                0,
                0
            ],
            [
                0,
                0,
                0
            ],
            [
                0,
                0,
                0
            ],
            [
                0,
                0,
                0
            ],
            [
                0,
                0,
                0
            ],
            [
                0,
                0,
                0
            ],
            [
                0,
                0,
                0
            ],
            [
                0,
                0,
                0
            ],
            [
                0,
                0,
                0
            ],
            [
                0,
                0,
                0
            ],
            [
                0,
                0,
                0
            ],
            [
                0,
                0,
                0
            ],
            [
                0,
                0,
                0
            ],
            [
                0,
                0,
                0
            ],
            [
                0,
                0,
                0
            ],
            [
                0,
                0,
                0
            ],
            [
                0,
                0,
                0
            ],
            [
                0,
                0,
                0
            ],
            [
                0,
                0,
                0
            ],
            [
                0,
                0,
                0
            ]
        ]
    ],
    "label": "U",
    "is_dual_hand": false,
    "augmented": true,
    "augmentation_methods": [
        "_apply_translation",
        "_apply_rotation",
        "_apply_noise",
        "_apply_scaling"
    ]
}