{
    "landmarks": [
        [
            [
                0.5370282096908767,
                0.8905975382969266,
                -0.052109603273136025
            ],
            [
                0.4939778305671765,
                0.8230775149574581,
                -0.05862843715068411
            ],
            [
                0.5064211435488029,
                0.7484600149463373,
                -0.07208252811146444
            ],
            [
                0.5552287167521703,
                0.712540864653672,
                -0.06861151087262579
            ],
            [
                0.6101718942734484,
                0.7243609490470649,
                -0.08900831640590415
            ],
            [
                0.5391490456758725,
                0.7244453515774734,
                -0.08433622838853139
            ],
            [
                0.5299679999233177,
                0.6183897481182783,
                -0.10654273622689664
            ],
            [
                0.5322827723067096,
                0.5650418650950615,
                -0.09783347668408196
            ],
            [
                0.5292676253471712,
                0.519940150149878,
                -0.12043104089231577
            ],
            [
                0.583147667105281,
                0.74188213362372,
                -0.08827073055613212
            ],
            [
                0.6038433930116432,
                0.6644378782333715,
                -0.09769932293954206
            ],
            [
                0.5884545986718913,
                0.6782083807961623,
                -0.09518134880533143
            ],
            [
                0.5796420975324451,
                0.6991884055740665,
                -0.09287099378085525
            ],
            [
                0.6156225579351413,
                0.7626774984537028,
                -0.08423444158055661
            ],
            [
                0.6198491702841761,
                0.7024281979185262,
                -0.1030918327955277
            ],
            [
                0.6152275276276548,
                0.7190659533903115,
                -0.09001793935249167
            ],
            [
                0.6021287192705462,
                0.7465283517760954,
                -0.07565129688694386
            ],
            [
                0.6570439821738261,
                0.7899494982414879,
                -0.09594300777596809
            ],
            [
                0.6383124158199139,
                0.7518244644469556,
                -0.0854239652275697
            ],
            [
                0.6235871602952041,
                0.746661790501678,
                -0.0819014416677457
            ],
            [
                0.6085330144744194,
                0.7674842753461375,
                -0.05660992132745016
            ]
        ],
        [
            [
                0,
                0,
                0
            ],
            [
                0,
                0,
                0
            ],
            [
                0,
                0,
                0
            ],
            [
                0,
                0,
                0
            ],
            [
                0,
                0,
                0
            ],
            [
                0,
                0,
                0
            ],
            [
                0,
                0,
                0
            ],
            [
                0,
                0,
                0
            ],
            [
                0,
                0,
                0
            ],
            [
                0,
                0,
                0
            ],
            [
                0,
                0,
                0
            ],
            [
                0,
                0,
                0
            ],
            [
                0,
                0,
                0
            ],
            [
                0,
                0,
                0
            ],
            [
                0,
                0,
                0
            ],
            [
                0,
                0,
                0
            ],
            [
                0,
                0,
                0
            ],
            [
                0,
                0,
                0
            ],
            [
                0,
                0,
                0
            ],
            [
                0,
                0,
                0
            ],
            [
                0,
                0,
                0
            ]
        ]
    ],
    "label": "Y",
    "is_dual_hand": false,
    "augmented": true,
    "augmentation_methods": [
        "_apply_translation",
        "_apply_noise",
        "_apply_scaling",
        "_apply_rotation"
    ]
}