{
    "landmarks": [
        [
            [
                0.5120901174748153,
                0.7250272464594522,
                0.042036683507239415
            ],
            [
                0.42515527601134084,
                0.7003142127714437,
                0.0016176310236215054
            ],
            [
                0.40168871445464277,
                0.5946221196873516,
                -0.008365217430183718
            ],
            [
                0.45449406349774185,
                0.5178675730361325,
                -0.028342111398088468
            ],
            [
                0.530417931310417,
                0.4919322710489786,
                -0.04196598291980972
            ],
            [
                0.4685351722386589,
                0.5242996651546347,
                -0.003832816165721571
            ],
            [
                0.47459941668986944,
                0.40102816876483227,
                -0.03804770140894441
            ],
            [
                0.48426333834791246,
                0.34382766761364353,
                -0.05189091617053392
            ],
            [
                0.490123008402913,
                0.27097576153992925,
                -0.05340894518033968
            ],
            [
                0.5284490160051603,
                0.5242022810731396,
                -0.0023760478896619006
            ],
            [
                0.560271362070703,
                0.406876539618476,
                -0.04045789573254408
            ],
            [
                0.5721627514518709,
                0.33281085556718987,
                -0.06425789934554799
            ],
            [
                0.594764344912079,
                0.2585134004355549,
                -0.07266929784557549
            ],
            [
                0.5843172897214814,
                0.5490756199003513,
                -0.018851318823088083
            ],
            [
                0.5909060887866666,
                0.46780390426094637,
                -0.07006189255427296
            ],
            [
                0.5491314086307746,
                0.47684121739979274,
                -0.06546863088740533
            ],
            [
                0.5160950255785534,
                0.5058137944189477,
                -0.03612834029915559
            ],
            [
                0.6222029288666615,
                0.5923030102932098,
                -0.027824708729286322
            ],
            [
                0.6711184192513298,
                0.5073670037467235,
                -0.055026737237597975
            ],
            [
                0.6995036872614349,
                0.44863270750586914,
                -0.08009206617832922
            ],
            [
                0.7182091942715669,
                0.400616847185384,
                -0.06334299733395603
            ]
        ],
        [
            [
                0,
                0,
                0
            ],
            [
                0,
                0,
                0
            ],
            [
                0,
                0,
                0
            ],
            [
                0,
                0,
                0
            ],
            [
                0,
                0,
                0
            ],
            [
                0,
                0,
                0
            ],
            [
                0,
                0,
                0
            ],
            [
                0,
                0,
                0
            ],
            [
                0,
                0,
                0
            ],
            [
                0,
                0,
                0
            ],
            [
                0,
                0,
                0
            ],
            [
                0,
                0,
                0
            ],
            [
                0,
                0,
                0
            ],
            [
                0,
                0,
                0
            ],
            [
                0,
                0,
                0
            ],
            [
                0,
                0,
                0
            ],
            [
                0,
                0,
                0
            ],
            [
                0,
                0,
                0
            ],
            [
                0,
                0,
                0
            ],
            [
                0,
                0,
                0
            ],
            [
                0,
                0,
                0
            ]
        ]
    ],
    "label": "7",
    "is_dual_hand": false,
    "augmented": true,
    "augmentation_methods": [
        "_apply_rotation",
        "_apply_translation",
        "_apply_noise"
    ]
}