{
    "landmarks": [
        [
            [
                0.7509819065299829,
                0.7284466829336498,
                -0.024116348082806258
            ],
            [
                0.6109794020617195,
                0.7500788689694059,
                -0.014559020910872397
            ],
            [
                0.47891586412937937,
                0.6812499229285833,
                -0.003312954321165018
            ],
            [
                0.38331501399006834,
                0.5915399919489711,
                0.02819382227863757
            ],
            [
                0.38483624440567854,
                0.5111179456706828,
                -0.013280117586893792
            ],
            [
                0.6016827268651052,
                0.4741296501318238,
                0.08068962682889613
            ],
            [
                0.5166578839662133,
                0.3983104595989837,
                0.05726849267648844
            ],
            [
                0.44307276944867036,
                0.4869039294351512,
                0.07994086350828894
            ],
            [
                0.4452493106849168,
                0.5112072440493804,
                0.04851992283378416
            ],
            [
                0.6254356412612496,
                0.41952339956407814,
                0.05185183635240924
            ],
            [
                0.506771655042305,
                0.3212912285292887,
                0.03631062863205855
            ],
            [
                0.4453647108425769,
                0.3792872400793347,
                0.002224164687117551
            ],
            [
                0.4207266113199847,
                0.48883955756790154,
                0.035764044758673535
            ],
            [
                0.647891492831716,
                0.37764244183005546,
                0.013932691881584816
            ],
            [
                0.48596838613954113,
                0.2531725410914226,
                -0.019357792642790334
            ],
            [
                0.39573694022253536,
                0.3720559594275297,
                -0.027808219452558045
            ],
            [
                0.3797014429008973,
                0.4438927455387227,
                -0.040831229508998514
            ],
            [
                0.6296968351310175,
                0.36125848726308973,
                -0.01557287693003074
            ],
            [
                0.5029085258673267,
                0.3224794347631694,
                -0.04077644873755851
            ],
            [
                0.38765440550908903,
                0.36574932535656035,
                -0.06855535774043135
            ],
            [
                0.4122104023093043,
                0.46532323130441877,
                -0.04227429709227926
            ]
        ],
        [
            [
                0,
                0,
                0
            ],
            [
                0,
                0,
                0
            ],
            [
                0,
                0,
                0
            ],
            [
                0,
                0,
                0
            ],
            [
                0,
                0,
                0
            ],
            [
                0,
                0,
                0
            ],
            [
                0,
                0,
                0
            ],
            [
                0,
                0,
                0
            ],
            [
                0,
                0,
                0
            ],
            [
                0,
                0,
                0
            ],
            [
                0,
                0,
                0
            ],
            [
                0,
                0,
                0
            ],
            [
                0,
                0,
                0
            ],
            [
                0,
                0,
                0
            ],
            [
                0,
                0,
                0
            ],
            [
                0,
                0,
                0
            ],
            [
                0,
                0,
                0
            ],
            [
                0,
                0,
                0
            ],
            [
                0,
                0,
                0
            ],
            [
                0,
                0,
                0
            ],
            [
                0,
                0,
                0
            ]
        ]
    ],
    "label": "O",
    "is_dual_hand": false,
    "augmented": true,
    "augmentation_methods": [
        "_apply_finger_variation",
        "_apply_noise",
        "_apply_translation",
        "_apply_rotation"
    ]
}