{
    "landmarks": [
        [
            [
                0.3849110740693063,
                0.6982828263200435,
                -0.00909712720179934
            ],
            [
                0.33781090774263,
                0.5814952142705012,
                -0.010534051059230708
            ],
            [
                0.3682030876375784,
                0.49536190144822984,
                -0.017765865756774392
            ],
            [
                0.4427932488031369,
                0.46980643382977877,
                -0.029198304989870513
            ],
            [
                0.5119595359064325,
                0.483487216738904,
                -0.04026055920987305
            ],
            [
                0.3993597488372954,
                0.43815244203157366,
                -0.07433043374805151
            ],
            [
                0.4263006900731885,
                0.2996571525230341,
                -0.11958448365254389
            ],
            [
                0.4486903616931461,
                0.20196868253756312,
                -0.12764475676298473
            ],
            [
                0.4759849908080626,
                0.13144754652082333,
                -0.14346922449104071
            ],
            [
                0.4822212049640046,
                0.47591088090496575,
                -0.09073652789835643
            ],
            [
                0.5483601357870285,
                0.35204878628119046,
                -0.12484610883428043
            ],
            [
                0.607824118195104,
                0.2600213195219447,
                -0.15048279509422308
            ],
            [
                0.6355397206136205,
                0.19058661239149777,
                -0.14651458787129598
            ],
            [
                0.5386787527508173,
                0.5206776172108197,
                -0.10199644726238224
            ],
            [
                0.6209264113220069,
                0.41116514544937643,
                -0.15223313044252604
            ],
            [
                0.6601747938080351,
                0.3349379527690823,
                -0.17239506974384983
            ],
            [
                0.7139871426279,
                0.29207696528114985,
                -0.17122830606063302
            ],
            [
                0.5701870551933441,
                0.5731344031610623,
                -0.08997753785313664
            ],
            [
                0.5812976703200478,
                0.5097108928720087,
                -0.11240758257476806
            ],
            [
                0.5429062580713747,
                0.5257559213375359,
                -0.10644730636482129
            ],
            [
                0.5154639799832282,
                0.5644705720613786,
                -0.0912392417907176
            ]
        ],
        [
            [
                0,
                0,
                0
            ],
            [
                0,
                0,
                0
            ],
            [
                0,
                0,
                0
            ],
            [
                0,
                0,
                0
            ],
            [
                0,
                0,
                0
            ],
            [
                0,
                0,
                0
            ],
            [
                0,
                0,
                0
            ],
            [
                0,
                0,
                0
            ],
            [
                0,
                0,
                0
            ],
            [
                0,
                0,
                0
            ],
            [
                0,
                0,
                0
            ],
            [
                0,
                0,
                0
            ],
            [
                0,
                0,
                0
            ],
            [
                0,
                0,
                0
            ],
            [
                0,
                0,
                0
            ],
            [
                0,
                0,
                0
            ],
            [
                0,
                0,
                0
            ],
            [
                0,
                0,
                0
            ],
            [
                0,
                0,
                0
            ],
            [
                0,
                0,
                0
            ],
            [
                0,
                0,
                0
            ]
        ]
    ],
    "label": "W",
    "is_dual_hand": false,
    "augmented": true,
    "augmentation_methods": [
        "_apply_rotation",
        "_apply_scaling",
        "_apply_noise"
    ]
}