{
    "landmarks": [
        [
            [
                0.39186301218659486,
                0.8580123080542699,
                -0.027822735687174402
            ],
            [
                0.32457460997646337,
                0.7179905442070819,
                -0.19098044851199092
            ],
            [
                0.3180502887882217,
                0.5171381001139876,
                -0.24713945389854353
            ],
            [
                0.31619019248650226,
                0.37276329012928544,
                -0.247573960293754
            ],
            [
                0.29335569511879095,
                0.24197126336325667,
                -0.24682941433326727
            ],
            [
                0.6367091859022816,
                0.5640104196743965,
                -0.21981172615597103
            ],
            [
                0.6646054583580957,
                0.3601085845974555,
                -0.20946437290119121
            ],
            [
                0.654430625787282,
                0.29198572259742195,
                -0.20872931523099597
            ],
            [
                0.6734880152816166,
                0.23813677387588303,
                -0.19820347189207074
            ],
            [
                0.6944586964932504,
                0.608929072256276,
                -0.11379576826691748
            ],
            [
                0.7124117168674882,
                0.38301467025376923,
                -0.1339755279461356
            ],
            [
                0.6930101607308662,
                0.26727839257747243,
                -0.1327765640992266
            ],
            [
                0.7028203457002528,
                0.1751493126904391,
                -0.13963876398929234
            ],
            [
                0.6986981437265575,
                0.640838918569361,
                -0.010180212929479232
            ],
            [
                0.6057264069830153,
                0.4745153722128135,
                -0.0509678061333786
            ],
            [
                0.5313157377066755,
                0.48178632665037946,
                -0.06500047749694028
            ],
            [
                0.48850261948648016,
                0.5604578695226728,
                -0.053608049538437896
            ],
            [
                0.6812627814427122,
                0.6534175130166356,
                0.07468697557600823
            ],
            [
                0.6237032942325761,
                0.5320380111641984,
                0.03395872458689877
            ],
            [
                0.5486459102903622,
                0.5526791224025432,
                0.015188065339560651
            ],
            [
                0.5206438601009034,
                0.6042012149609877,
                0.01916774160498174
            ]
        ],
        [
            [
                0,
                0,
                0
            ],
            [
                0,
                0,
                0
            ],
            [
                0,
                0,
                0
            ],
            [
                0,
                0,
                0
            ],
            [
                0,
                0,
                0
            ],
            [
                0,
                0,
                0
            ],
            [
                0,
                0,
                0
            ],
            [
                0,
                0,
                0
            ],
            [
                0,
                0,
                0
            ],
            [
                0,
                0,
                0
            ],
            [
                0,
                0,
                0
            ],
            [
                0,
                0,
                0
            ],
            [
                0,
                0,
                0
            ],
            [
                0,
                0,
                0
            ],
            [
                0,
                0,
                0
            ],
            [
                0,
                0,
                0
            ],
            [
                0,
                0,
                0
            ],
            [
                0,
                0,
                0
            ],
            [
                0,
                0,
                0
            ],
            [
                0,
                0,
                0
            ],
            [
                0,
                0,
                0
            ]
        ]
    ],
    "label": "U",
    "is_dual_hand": false,
    "augmented": true,
    "augmentation_methods": [
        "_apply_translation",
        "_apply_noise",
        "_apply_rotation"
    ]
}