{
    "landmarks": [
        [
            [
                0.5021676773640887,
                0.6206095557537005,
                -0.0014065444206564377
            ],
            [
                0.5549837668366359,
                0.5802947185823567,
                -0.038117752377688614
            ],
            [
                0.615997288564219,
                0.5253628141833446,
                -0.032072547445580045
            ],
            [
                0.6224209577968224,
                0.45434587407786514,
                -0.06936692816838907
            ],
            [
                0.6505420392750448,
                0.38383882565668903,
                -0.07463000700595551
            ],
            [
                0.5320049158409674,
                0.4336495047715669,
                -0.04332677852724999
            ],
            [
                0.5202102618167058,
                0.369641248926261,
                -0.0706809030245329
            ],
            [
                0.5263380095571282,
                0.3164880970623011,
                -0.06664816926634727
            ],
            [
                0.5014284075381277,
                0.24141816365411192,
                -0.0487165125839337
            ],
            [
                0.4838462740667252,
                0.44018865420623027,
                -0.03090805947071687
            ],
            [
                0.46932924663386505,
                0.3814426894120935,
                -0.031602092458334924
            ],
            [
                0.4581827876939488,
                0.31848874598224414,
                -0.06966140248354089
            ],
            [
                0.39965856874493777,
                0.31833221402177814,
                -0.0699502626985699
            ],
            [
                0.4353912159070581,
                0.469177858471426,
                -0.037005320206238076
            ],
            [
                0.4388941629580315,
                0.4340256696594803,
                -0.10036064663527774
            ],
            [
                0.4041700752428701,
                0.4757258210990056,
                -0.05284003979050976
            ],
            [
                0.41505756624761914,
                0.5126282527647041,
                -0.07857779175384261
            ],
            [
                0.40474858406726505,
                0.5060536672699252,
                -0.04872291725341078
            ],
            [
                0.36934389394102224,
                0.46720220549753866,
                -0.09818231699224406
            ],
            [
                0.43892507005463405,
                0.5215448356843874,
                -0.08630349265827116
            ],
            [
                0.44804700024967975,
                0.5215250882273698,
                -0.08876827153972781
            ]
        ],
        [
            [
                0,
                0,
                0
            ],
            [
                0,
                0,
                0
            ],
            [
                0,
                0,
                0
            ],
            [
                0,
                0,
                0
            ],
            [
                0,
                0,
                0
            ],
            [
                0,
                0,
                0
            ],
            [
                0,
                0,
                0
            ],
            [
                0,
                0,
                0
            ],
            [
                0,
                0,
                0
            ],
            [
                0,
                0,
                0
            ],
            [
                0,
                0,
                0
            ],
            [
                0,
                0,
                0
            ],
            [
                0,
                0,
                0
            ],
            [
                0,
                0,
                0
            ],
            [
                0,
                0,
                0
            ],
            [
                0,
                0,
                0
            ],
            [
                0,
                0,
                0
            ],
            [
                0,
                0,
                0
            ],
            [
                0,
                0,
                0
            ],
            [
                0,
                0,
                0
            ],
            [
                0,
                0,
                0
            ]
        ]
    ],
    "label": "3",
    "is_dual_hand": false,
    "augmented": true,
    "augmentation_methods": [
        "_apply_scaling",
        "_apply_finger_variation",
        "_apply_translation",
        "_apply_noise"
    ]
}