{
    "landmarks": [
        [
            [
                0.4863219725010445,
                0.6171232656380375,
                0.013686140428084831
            ],
            [
                0.4356722913921565,
                0.5777991495386705,
                -0.0136162121545133
            ],
            [
                0.41905736817809075,
                0.5010994983887609,
                -0.023745305973614357
            ],
            [
                0.46213102573197806,
                0.40557904848457715,
                -0.04887653926317789
            ],
            [
                0.5363542380367966,
                0.3866913391358765,
                -0.027693292462610417
            ],
            [
                0.500361899416972,
                0.44266215852712804,
                -0.022785029338618056
            ],
            [
                0.5644780676969091,
                0.38637355797771816,
                -0.028841822149628105
            ],
            [
                0.6026152856270972,
                0.2887428419526913,
                -0.10478016885658173
            ],
            [
                0.6455666635497616,
                0.22465272322027843,
                -0.09884318719833672
            ],
            [
                0.5723332182938338,
                0.46717925439170327,
                -0.03825210463780905
            ],
            [
                0.5584235075985235,
                0.38836619640389813,
                -0.08126422015668316
            ],
            [
                0.5549145543343573,
                0.44169728946407294,
                -0.08378200992608947
            ],
            [
                0.5392057946926059,
                0.4623518383490531,
                -0.09584183125527565
            ],
            [
                0.6181236705648008,
                0.48938801111272967,
                -0.059103013783860556
            ],
            [
                0.6065765496471016,
                0.38637211241285746,
                -0.10061464590300856
            ],
            [
                0.560691120990745,
                0.4426651336334784,
                -0.12364986946722253
            ],
            [
                0.5271777286206021,
                0.43645668027187445,
                -0.0767371477861769
            ],
            [
                0.6555168116975869,
                0.5289864383663965,
                -0.06460574957679838
            ],
            [
                0.7253906821159863,
                0.45286937571200697,
                -0.12170795544767501
            ],
            [
                0.7534882697843552,
                0.3977464726076198,
                -0.11732666215593285
            ],
            [
                0.8315400911290534,
                0.381257289489407,
                -0.11546422382195798
            ]
        ],
        [
            [
                0,
                0,
                0
            ],
            [
                0,
                0,
                0
            ],
            [
                0,
                0,
                0
            ],
            [
                0,
                0,
                0
            ],
            [
                0,
                0,
                0
            ],
            [
                0,
                0,
                0
            ],
            [
                0,
                0,
                0
            ],
            [
                0,
                0,
                0
            ],
            [
                0,
                0,
                0
            ],
            [
                0,
                0,
                0
            ],
            [
                0,
                0,
                0
            ],
            [
                0,
                0,
                0
            ],
            [
                0,
                0,
                0
            ],
            [
                0,
                0,
                0
            ],
            [
                0,
                0,
                0
            ],
            [
                0,
                0,
                0
            ],
            [
                0,
                0,
                0
            ],
            [
                0,
                0,
                0
            ],
            [
                0,
                0,
                0
            ],
            [
                0,
                0,
                0
            ],
            [
                0,
                0,
                0
            ]
        ]
    ],
    "label": "7",
    "is_dual_hand": false,
    "augmented": true,
    "augmentation_methods": [
        "_apply_finger_variation",
        "_apply_noise",
        "_apply_scaling",
        "_apply_rotation"
    ]
}