{
    "landmarks": [
        [
            [
                0.7436465649884072,
                0.4914283969802228,
                -0.009542146843781766
            ],
            [
                0.706089356950798,
                0.4895358247363634,
                -0.1155091579307759
            ],
            [
                0.6561849579715174,
                0.45404116036863795,
                -0.1908558041590211
            ],
            [
                0.5379721200047638,
                0.4207337146804913,
                -0.15894983784574984
            ],
            [
                0.48243396885080986,
                0.4399086944423558,
                -0.2212418175735573
            ],
            [
                0.7044560626023547,
                0.2997805753043334,
                -0.14478579798518995
            ],
            [
                0.6164333393598606,
                0.24603364889718085,
                -0.1851753692250614
            ],
            [
                0.4965591254328388,
                0.30341147141398944,
                -0.18421087639950706
            ],
            [
                0.5288802436601683,
                0.3321533756894414,
                -0.19450137505541693
            ],
            [
                0.7067009426908053,
                0.29161647936737234,
                -0.09605799728851237
            ],
            [
                0.6233924696447728,
                0.3251388240444398,
                -0.14186462038996986
            ],
            [
                0.6084248873601552,
                0.37834588254899365,
                -0.12642634617628778
            ],
            [
                0.629096375072245,
                0.380447401741966,
                -0.13650561812122772
            ],
            [
                0.7075387763886645,
                0.3054776725288069,
                -0.052960857091202476
            ],
            [
                0.6138402984071826,
                0.34943826526210114,
                -0.11103493674755335
            ],
            [
                0.6063753056966555,
                0.3718330044315172,
                -0.1191302598497274
            ],
            [
                0.6482944313795496,
                0.3749959669383864,
                -0.08109672453648181
            ],
            [
                0.7058736034348297,
                0.2986133716054866,
                -0.01599295794574556
            ],
            [
                0.5890819622670936,
                0.3258538381438482,
                -0.05391536790272625
            ],
            [
                0.6088593243589507,
                0.34526638594112286,
                -0.08800815223897124
            ],
            [
                0.6453786967229427,
                0.3610610220817346,
                -0.07879422714137928
            ]
        ],
        [
            [
                0,
                0,
                0
            ],
            [
                0,
                0,
                0
            ],
            [
                0,
                0,
                0
            ],
            [
                0,
                0,
                0
            ],
            [
                0,
                0,
                0
            ],
            [
                0,
                0,
                0
            ],
            [
                0,
                0,
                0
            ],
            [
                0,
                0,
                0
            ],
            [
                0,
                0,
                0
            ],
            [
                0,
                0,
                0
            ],
            [
                0,
                0,
                0
            ],
            [
                0,
                0,
                0
            ],
            [
                0,
                0,
                0
            ],
            [
                0,
                0,
                0
            ],
            [
                0,
                0,
                0
            ],
            [
                0,
                0,
                0
            ],
            [
                0,
                0,
                0
            ],
            [
                0,
                0,
                0
            ],
            [
                0,
                0,
                0
            ],
            [
                0,
                0,
                0
            ],
            [
                0,
                0,
                0
            ]
        ]
    ],
    "label": "Q",
    "is_dual_hand": false,
    "augmented": true,
    "augmentation_methods": [
        "_apply_noise",
        "_apply_rotation",
        "_apply_finger_variation"
    ]
}