{
    "landmarks": [
        [
            [
                0.4709553931386178,
                0.8203917858828763,
                -0.006452703621424699
            ],
            [
                0.4235618541420325,
                0.8211231316433322,
                -0.05841998414162257
            ],
            [
                0.3700813052342458,
                0.7910702231684023,
                -0.08606390302956136
            ],
            [
                0.3941088259767771,
                0.7350585627894873,
                -0.09535022410689968
            ],
            [
                0.48356888548401644,
                0.7006848456271667,
                -0.08845071432690844
            ],
            [
                0.3756461539614382,
                0.6413652941849297,
                -0.06515451901772078
            ],
            [
                0.3232607238427625,
                0.5713639436423981,
                -0.10984183670615086
            ],
            [
                0.34293600815867403,
                0.49955112881170877,
                -0.10619823178277242
            ],
            [
                0.27677309190379545,
                0.41690559815658124,
                -0.1473321599902115
            ],
            [
                0.4251306662277414,
                0.6323942714953905,
                -0.06666342169789533
            ],
            [
                0.45181417779694644,
                0.5232525713889126,
                -0.08683810123587729
            ],
            [
                0.44432409647993376,
                0.45611246924676574,
                -0.10243279466683836
            ],
            [
                0.408726582698425,
                0.3713388472314604,
                -0.10576828211624639
            ],
            [
                0.47545990504146096,
                0.6548007164091686,
                -0.07741743022346449
            ],
            [
                0.47220414675455585,
                0.5499957134227024,
                -0.0794361616406469
            ],
            [
                0.47121118682994445,
                0.48654874080948135,
                -0.14006485299015875
            ],
            [
                0.4840261967215286,
                0.46312288470571317,
                -0.1796735197422578
            ],
            [
                0.5162728234696639,
                0.6783354087078876,
                -0.07175792059082438
            ],
            [
                0.505030105088746,
                0.6420566492426762,
                -0.10735199576055829
            ],
            [
                0.538905731686241,
                0.6902722402079539,
                -0.1614411759588755
            ],
            [
                0.5006325634229971,
                0.7494686709319072,
                -0.11041303857288162
            ]
        ],
        [
            [
                0,
                0,
                0
            ],
            [
                0,
                0,
                0
            ],
            [
                0,
                0,
                0
            ],
            [
                0,
                0,
                0
            ],
            [
                0,
                0,
                0
            ],
            [
                0,
                0,
                0
            ],
            [
                0,
                0,
                0
            ],
            [
                0,
                0,
                0
            ],
            [
                0,
                0,
                0
            ],
            [
                0,
                0,
                0
            ],
            [
                0,
                0,
                0
            ],
            [
                0,
                0,
                0
            ],
            [
                0,
                0,
                0
            ],
            [
                0,
                0,
                0
            ],
            [
                0,
                0,
                0
            ],
            [
                0,
                0,
                0
            ],
            [
                0,
                0,
                0
            ],
            [
                0,
                0,
                0
            ],
            [
                0,
                0,
                0
            ],
            [
                0,
                0,
                0
            ],
            [
                0,
                0,
                0
            ]
        ]
    ],
    "label": "6",
    "is_dual_hand": false,
    "augmented": true,
    "augmentation_methods": [
        "_apply_noise",
        "_apply_rotation",
        "_apply_finger_variation"
    ]
}