{
    "landmarks": [
        [
            [
                0.8344349798894355,
                0.42940038248488394,
                -0.019716357195157012
            ],
            [
                0.7531841988322686,
                0.44775048164959713,
                -0.006146804539048936
            ],
            [
                0.6965438896329269,
                0.4896171571441609,
                -0.02390865288618093
            ],
            [
                0.6632610694607064,
                0.5587246197291016,
                -0.03409872294358989
            ],
            [
                0.6532330044798114,
                0.6129247774230381,
                -0.05089866863986808
            ],
            [
                0.6592902853692906,
                0.49955672818194397,
                -0.047714932301903865
            ],
            [
                0.6204236900812703,
                0.6047580863458595,
                -0.0812857190542535
            ],
            [
                0.6489018831057499,
                0.6552743051053308,
                -0.09415124006656655
            ],
            [
                0.6677041935903114,
                0.6646413621502621,
                -0.10080410720688524
            ],
            [
                0.694021476441842,
                0.49377143550601343,
                -0.08204872379082034
            ],
            [
                0.6694928092199485,
                0.6468051281149021,
                -0.10193139216421046
            ],
            [
                0.7096726946722255,
                0.6491040177883945,
                -0.0932356443518329
            ],
            [
                0.7105658271327214,
                0.6079423625010133,
                -0.09004014628351559
            ],
            [
                0.7390482027156435,
                0.5094207973086,
                -0.08588248684692301
            ],
            [
                0.7436302957825504,
                0.6455113810861551,
                -0.10761558322385648
            ],
            [
                0.7602248911989684,
                0.6129246407876793,
                -0.09822470728781552
            ],
            [
                0.7711006590883744,
                0.5920874323509314,
                -0.09831275064797187
            ],
            [
                0.8050024302886811,
                0.529562953730991,
                -0.11976328994524324
            ],
            [
                0.7951352417186791,
                0.6247107461478124,
                -0.12780865670032932
            ],
            [
                0.8149983930348881,
                0.6057498722398651,
                -0.11718974155397557
            ],
            [
                0.8213197404436812,
                0.5708331415700391,
                -0.11192696164543392
            ]
        ],
        [
            [
                0,
                0,
                0
            ],
            [
                0,
                0,
                0
            ],
            [
                0,
                0,
                0
            ],
            [
                0,
                0,
                0
            ],
            [
                0,
                0,
                0
            ],
            [
                0,
                0,
                0
            ],
            [
                0,
                0,
                0
            ],
            [
                0,
                0,
                0
            ],
            [
                0,
                0,
                0
            ],
            [
                0,
                0,
                0
            ],
            [
                0,
                0,
                0
            ],
            [
                0,
                0,
                0
            ],
            [
                0,
                0,
                0
            ],
            [
                0,
                0,
                0
            ],
            [
                0,
                0,
                0
            ],
            [
                0,
                0,
                0
            ],
            [
                0,
                0,
                0
            ],
            [
                0,
                0,
                0
            ],
            [
                0,
                0,
                0
            ],
            [
                0,
                0,
                0
            ],
            [
                0,
                0,
                0
            ]
        ]
    ],
    "label": "K",
    "is_dual_hand": false,
    "augmented": true,
    "augmentation_methods": [
        "_apply_scaling",
        "_apply_noise",
        "_apply_translation",
        "_apply_rotation"
    ]
}