{
    "landmarks": [
        [
            [
                0.8314015720029809,
                0.3560173154663296,
                0.008997168773194578
            ],
            [
                0.7904330617909576,
                0.21662221457201808,
                -0.05697399119859822
            ],
            [
                0.6437581862661329,
                0.10451295162615096,
                -0.04516524932916933
            ],
            [
                0.5213270710114392,
                0.11808885897986529,
                -0.07462457797740439
            ],
            [
                0.4636045917514843,
                0.11085575095170694,
                -0.08427323324027315
            ],
            [
                0.4853262037248349,
                0.2007462947829355,
                -0.007782348132735213
            ],
            [
                0.35497194735799925,
                0.16031162500174828,
                -0.03361816154431007
            ],
            [
                0.2383146540111402,
                0.16861284709142332,
                -0.07079822730267317
            ],
            [
                0.1997864841295613,
                0.21478131077945556,
                -0.09958231695122438
            ],
            [
                0.46266991201364166,
                0.2818304416159412,
                0.0019232644169412394
            ],
            [
                0.2889089805892929,
                0.2867600199830016,
                -0.02001585972996575
            ],
            [
                0.1778893343231185,
                0.262454446922733,
                -0.032320849966684065
            ],
            [
                0.09817488858373297,
                0.23504976263021068,
                -0.08235867339122585
            ],
            [
                0.46880550966241874,
                0.3583160982541649,
                0.0018516165585967526
            ],
            [
                0.33810435729805877,
                0.37162946998366136,
                -0.030624175062262622
            ],
            [
                0.22896284396351724,
                0.33415620483707587,
                -0.04136703572102758
            ],
            [
                0.14398974524908167,
                0.35388313519897174,
                -0.0854933670251723
            ],
            [
                0.49905112294792064,
                0.43789137609075734,
                -0.005276197863820387
            ],
            [
                0.36985610673962127,
                0.4509171347342112,
                -0.01874634904644879
            ],
            [
                0.31305420549321283,
                0.3994971036381955,
                -0.07491744165673864
            ],
            [
                0.23782421754253358,
                0.38087465144759197,
                -0.03085090068496222
            ]
        ],
        [
            [
                0,
                0,
                0
            ],
            [
                0,
                0,
                0
            ],
            [
                0,
                0,
                0
            ],
            [
                0,
                0,
                0
            ],
            [
                0,
                0,
                0
            ],
            [
                0,
                0,
                0
            ],
            [
                0,
                0,
                0
            ],
            [
                0,
                0,
                0
            ],
            [
                0,
                0,
                0
            ],
            [
                0,
                0,
                0
            ],
            [
                0,
                0,
                0
            ],
            [
                0,
                0,
                0
            ],
            [
                0,
                0,
                0
            ],
            [
                0,
                0,
                0
            ],
            [
                0,
                0,
                0
            ],
            [
                0,
                0,
                0
            ],
            [
                0,
                0,
                0
            ],
            [
                0,
                0,
                0
            ],
            [
                0,
                0,
                0
            ],
            [
                0,
                0,
                0
            ],
            [
                0,
                0,
                0
            ]
        ]
    ],
    "label": "R",
    "is_dual_hand": false,
    "augmented": true,
    "augmentation_methods": [
        "_apply_finger_variation",
        "_apply_translation",
        "_apply_rotation",
        "_apply_scaling"
    ]
}