{
    "landmarks": [
        [
            [
                0.2092197554996279,
                0.6783910621862537,
                0.014253261062966899
            ],
            [
                0.3486374701837669,
                0.6148225087109453,
                -0.044965332717616574
            ],
            [
                0.4718658857416699,
                0.5287756585445382,
                -0.05063778991447186
            ],
            [
                0.5293065851472624,
                0.42678375241625294,
                -0.10994109333152936
            ],
            [
                0.5630379620890638,
                0.3368314003079397,
                -0.12046100503970678
            ],
            [
                0.3829823345965673,
                0.43403627257314814,
                -0.10841463143023684
            ],
            [
                0.5216515213093277,
                0.5812227648358975,
                -0.16882169470748062
            ],
            [
                0.48638600790911046,
                0.6143186616964185,
                -0.20332894728405454
            ],
            [
                0.4207468937192214,
                0.614361615555177,
                -0.22251821773457814
            ],
            [
                0.29056850387199906,
                0.48143776895900153,
                -0.11096556516393968
            ],
            [
                0.4168247381921172,
                0.6767581195340459,
                -0.19196703317024522
            ],
            [
                0.40145279316840227,
                0.6996755301779253,
                -0.1453318131856996
            ],
            [
                0.39169397645417314,
                0.7024726027138736,
                -0.18953649185854377
            ],
            [
                0.21511631920260074,
                0.554330356004157,
                -0.11768037904364244
            ],
            [
                0.35192408007942083,
                0.7143028077672714,
                -0.200431456739878
            ],
            [
                0.3596903649250692,
                0.7257962337307317,
                -0.18308581814941083
            ],
            [
                0.32270731688043963,
                0.7271223098396609,
                -0.14887101423733684
            ],
            [
                0.1553573292418932,
                0.6301594512407304,
                -0.12964341677262656
            ],
            [
                0.23605857298396507,
                0.7235583403701318,
                -0.186793598991035
            ],
            [
                0.2898885933061181,
                0.7603358407297602,
                -0.14768515863789242
            ],
            [
                0.2175924562607504,
                0.7703908346468715,
                -0.1750359360536971
            ]
        ],
        [
            [
                0,
                0,
                0
            ],
            [
                0,
                0,
                0
            ],
            [
                0,
                0,
                0
            ],
            [
                0,
                0,
                0
            ],
            [
                0,
                0,
                0
            ],
            [
                0,
                0,
                0
            ],
            [
                0,
                0,
                0
            ],
            [
                0,
                0,
                0
            ],
            [
                0,
                0,
                0
            ],
            [
                0,
                0,
                0
            ],
            [
                0,
                0,
                0
            ],
            [
                0,
                0,
                0
            ],
            [
                0,
                0,
                0
            ],
            [
                0,
                0,
                0
            ],
            [
                0,
                0,
                0
            ],
            [
                0,
                0,
                0
            ],
            [
                0,
                0,
                0
            ],
            [
                0,
                0,
                0
            ],
            [
                0,
                0,
                0
            ],
            [
                0,
                0,
                0
            ],
            [
                0,
                0,
                0
            ]
        ]
    ],
    "label": "A",
    "is_dual_hand": false,
    "augmented": true,
    "augmentation_methods": [
        "_apply_translation",
        "_apply_finger_variation",
        "_apply_scaling",
        "_apply_rotation"
    ]
}